logger_cloudwatch_structlog/__init__.py
logger_cloudwatch_structlog/custom_processors.py
logger_cloudwatch_structlog/functions.py
logger_cloudwatch_structlog-0.1.1.dist-info/LICENSE
logger_cloudwatch_structlog-0.1.1.dist-info/METADATA
logger_cloudwatch_structlog-0.1.1.dist-info/NOTICE
logger_cloudwatch_structlog-0.1.1.dist-info/WHEEL
logger_cloudwatch_structlog-0.1.1.dist-info/top_level.txt
logger_cloudwatch_structlog-0.1.1.dist-info/RECORD
