Metadata-Version: 2.1
Name: logger-cloudwatch-structlog
Version: 0.1.1
Summary: Python library that allows logging in an AWS CloudWatch compatible way using a json format in serverless services (e.g. AWS Lambda). It is easily readable by humans and machines.
Home-page: https://github.com/kitchenita/python-logger-cloudwatch-structlog
Author: Kitchenita, Facundo A. Lucianna
Author-email: facundolucianna@gmail.com
Project-URL: Bug Tracker, https://github.com/kitchenita/python-logger-cloudwatch-structlog/issues
License-File: LICENSE
License-File: NOTICE
Requires-Dist: structlog (>=22.2)
